quickdocs/__init__.py
quickdocs/__main__.py
quickdocs/exceptions/__init__.py
quickdocs/exceptions/files.py
quickdocs/exceptions/inputs.py
quickdocs/state/__init__.py
quickdocs/state/inputs.py
quickdocs/state/paths.py
quickdocs/templates/conf.j2
quickdocs/templates/index.j2
quickdocs/templates/requirements.txt
quickdocs/templates/static/favicon.ico
quickdocs/templates/static/quickdocs.css
quickdocs/utils/__init__.py
quickdocs/utils/dicts.py
quickdocs/utils/files.py
quickdocs/utils/jinja.py
quickdocs/utils/paths.py
quickdocs/utils/types.py
quickdocs-1.6.3.dist-info/LICENSE.md
quickdocs-1.6.3.dist-info/METADATA
quickdocs-1.6.3.dist-info/WHEEL
quickdocs-1.6.3.dist-info/entry_points.txt
quickdocs-1.6.3.dist-info/top_level.txt
quickdocs-1.6.3.dist-info/RECORD
