Metadata-Version: 2.1
Name: quickdocs
Version: 1.6.3
Summary: Creates HTML docs from a project's readme and sphinx-apidoc.
Home-page: https://github.com/JoelLefkowitz/quickdocs
Author: Joel Lefkowitz
Author-email: joellefkowitz@hotmail.com
License: UNKNOWN
Keywords: docs,documents,sphinx,autodoc,apidoc
Platform: UNKNOWN
Classifier: License :: OSI Approved :: MIT License
Classifier: Programming Language :: Python :: 3.6
Classifier: Programming Language :: Python :: 3.7
Classifier: Programming Language :: Python :: 3.8
Requires-Python: >=3.6
Requires-Dist: dataclasses
Requires-Dist: pyimport
Requires-Dist: pypandoc
Requires-Dist: ruamel.yaml
Requires-Dist: simple-pipes
Requires-Dist: sphinx-autodoc-annotation
Requires-Dist: sphinx
Requires-Dist: sphinxcontrib.apidoc
Requires-Dist: sphinxcontrib.pandoc-markdown
Requires-Dist: walkmate
Requires-Dist: yummy-sphinx-theme
Provides-Extra: tests
Requires-Dist: coverage ; extra == 'tests'
Requires-Dist: codacy-coverage ; extra == 'tests'
Requires-Dist: pytest-bdd ; extra == 'tests'
Requires-Dist: pytest-cov ; extra == 'tests'
Requires-Dist: pytest-html ; extra == 'tests'
Requires-Dist: pytest-sugar ; extra == 'tests'
Requires-Dist: pytest-watch ; extra == 'tests'
Requires-Dist: pytest ; extra == 'tests'
Requires-Dist: tox-travis ; extra == 'tests'
Requires-Dist: tox ; extra == 'tests'
Provides-Extra: tools
Requires-Dist: autoflake ; extra == 'tools'
Requires-Dist: bandit ; extra == 'tools'
Requires-Dist: black ; extra == 'tools'
Requires-Dist: bump2version ; extra == 'tools'
Requires-Dist: isort ; extra == 'tools'
Requires-Dist: mypy ; extra == 'tools'
Requires-Dist: pylint ; extra == 'tools'
Requires-Dist: quickdocs ; extra == 'tools'
Requires-Dist: twine ; extra == 'tools'
Requires-Dist: wheel ; extra == 'tools'
